sentiment_analysis/__init__.py
sentiment_analysis/cleaner.py
sentiment_analysis/sentiment_analysis.py
sentiment_analysis/test_sentiment_analysis.py
sentimentspanish-0.0.2.dist-info/LICENSE
sentimentspanish-0.0.2.dist-info/METADATA
sentimentspanish-0.0.2.dist-info/WHEEL
sentimentspanish-0.0.2.dist-info/top_level.txt
sentimentspanish-0.0.2.dist-info/RECORD
