Metadata-Version: 2.1
Name: sentimentspanish
Version: 0.0.2
Summary: Sentiment analysis for sentences in spanish
Home-page: https://github.com/sentiment-analysis-spanish/sentiment-spanish
Author: Hugo J. Bello
Author-email: hjbello.wk@gmail.com
License: UNKNOWN
Platform: UNKNOWN
Classifier: Programming Language :: Python :: 3
Classifier: License :: OSI Approved :: MIT License
Classifier: Operating System :: OS Independent
